app/__init__.py
dataless-1.1.dist-info/LICENSE
dataless-1.1.dist-info/METADATA
dataless-1.1.dist-info/WHEEL
dataless-1.1.dist-info/top_level.txt
dataless-1.1.dist-info/RECORD
