Metadata-Version: 2.1
Name: dataless
Version: 1.1
Summary: Library for Implementation of the dataless Neural Network for range of NP-hard problems
Author: Azib Farooq
Classifier: Programming Language :: Python :: 3
Classifier: License :: OSI Approved :: MIT License
License-File: LICENSE
